tetrachotomy/__init__.py
tetrachotomy/tetrachotomy.py
tetrachotomy-1.0.0.dist-info/LICENSE.txt
tetrachotomy-1.0.0.dist-info/METADATA
tetrachotomy-1.0.0.dist-info/WHEEL
tetrachotomy-1.0.0.dist-info/top_level.txt
tetrachotomy-1.0.0.dist-info/RECORD
