Metadata-Version: 2.1
Name: tetrachotomy
Version: 1.0.0
Summary: Hunting poles and zeros in the complex plane
Author-email: Benjamin Vial <benjamin.vial84@gmail.com>
Maintainer-email: Benjamin Vial <benjamin.vial84@gmail.com>
License: GNU GENERAL PUBLIC LICENSE
Project-URL: Homepage, https://github.com/benvial/tetrachotomy
Project-URL: Bug Reports, https://github.com/benvial/tetrachotomy/issues
Project-URL: Source, https://github.com/benvial/tetrachotomy
Keywords: zeros search,zeros search,complex analysis
Classifier: Development Status :: 5 - Production/Stable
Classifier: Intended Audience :: Science/Research
Classifier: License :: OSI Approved :: GNU General Public License v3 or later (GPLv3+)
Classifier: Operating System :: OS Independent
Classifier: Programming Language :: Python
Classifier: Programming Language :: Python :: 3
Classifier: Programming Language :: Python :: 3.6
Classifier: Programming Language :: Python :: 3.7
Classifier: Programming Language :: Python :: 3.8
Classifier: Programming Language :: Python :: 3.9
Classifier: Programming Language :: Python :: 3.10
Classifier: Programming Language :: Python :: 3.11
Classifier: Programming Language :: Python :: 3.12
Classifier: Topic :: Scientific/Engineering
Classifier: Topic :: Scientific/Engineering :: Mathematics
Classifier: Topic :: Utilities
Requires-Python: >=3.6
License-File: LICENSE.txt
Requires-Dist: numpy
Provides-Extra: plot
Requires-Dist: matplotlib ; extra == 'plot'
